funds/__init__.py
funds/util.py
funds-0.0.3.dist-info/LICENSE
funds-0.0.3.dist-info/METADATA
funds-0.0.3.dist-info/WHEEL
funds-0.0.3.dist-info/top_level.txt
funds-0.0.3.dist-info/RECORD
