Metadata-Version: 2.1
Name: funds
Version: 0.0.3
Summary: Historical finance data data and caching
Home-page: https://github.com/thorwhalen/funds
Author: Thor Whalen
License: apache-2.0
Platform: any
Requires-Dist: importlib-resources
